ruspectroscopy_tools.libs/libgomp-2a14883a.so.1.0.0
rusmodules/eigenvals.py
rusmodules/inverse.py
rusmodules/rus.cpython-312-i386-linux-musl.so
rusmodules/data_generation.py
rusmodules/__init__.py
rusmodules/geometry.py
ruspectroscopy_tools-0.0.3.dist-info/WHEEL
ruspectroscopy_tools-0.0.3.dist-info/top_level.txt
ruspectroscopy_tools-0.0.3.dist-info/METADATA
ruspectroscopy_tools-0.0.3.dist-info/RECORD
ruspectroscopy_tools-0.0.3.dist-info/licenses/LICENSE
