Metadata-Version: 2.4
Name: ruspectroscopy_tools
Version: 0.0.3
Summary: A tool to solve the inverse problem in RUS (Resonant Ultrasound Spectroscopy) of cubic materials using Machine Learning
Home-page: https://github.com/cubos-d/RUSpectroscopy_Tools
Author: Alejandro Cubillos
Author-email: alejandro4cm@gmail.com
License: MIT
Classifier: Programming Language :: Python :: 3
Classifier: License :: OSI Approved :: MIT License
Classifier: Operating System :: OS Independent
Requires-Python: >=3.12
License-File: LICENSE
Requires-Dist: numpy
Requires-Dist: pandas
Requires-Dist: scipy
Requires-Dist: matplotlib
Dynamic: author
Dynamic: author-email
Dynamic: classifier
Dynamic: description
Dynamic: description-content-type
Dynamic: home-page
Dynamic: license
Dynamic: license-file
Dynamic: requires-dist
Dynamic: requires-python
Dynamic: summary
